forestiler/__init__.py
forestiler/chipIO.py
forestiler/forestile.py
forestiler/mask.py
forestiler-0.2.2.dist-info/LICENSE
forestiler-0.2.2.dist-info/METADATA
forestiler-0.2.2.dist-info/WHEEL
forestiler-0.2.2.dist-info/entry_points.txt
forestiler-0.2.2.dist-info/RECORD
