Metadata-Version: 2.1
Name: forestiler
Version: 0.2.2
Summary: Create Image Tiles From Large Input Rasters According to a Classified Mask Vector File
Home-page: https://github.com/Florian-Katerndahl/ForesTiler
License: GPL-2.0-only
Keywords: remote sensing,image processing,data preparation
Author: Florian Katerndahl
Author-email: florian@katerndahl.com
Requires-Python: >=3.9,<4.0
Classifier: Development Status :: 4 - Beta
Classifier: Environment :: Console
Classifier: Intended Audience :: Science/Research
Classifier: License :: OSI Approved :: GNU General Public License v2 (GPLv2)
Classifier: Natural Language :: English
Classifier: Operating System :: OS Independent
Classifier: Programming Language :: Python :: 3
Classifier: Programming Language :: Python :: 3.9
Classifier: Programming Language :: Python :: 3.10
Classifier: Programming Language :: Python :: 3.11
Classifier: Programming Language :: Python :: 3.12
Classifier: Topic :: Scientific/Engineering :: GIS
Classifier: Topic :: Scientific/Engineering :: Image Processing
Requires-Dist: geopandas (>=0.14.4,<0.15.0)
Requires-Dist: numpy (>=1.26.4,<2.0.0)
Requires-Dist: pillow (>=10.3.0,<11.0.0)
Requires-Dist: psutil (>=6.0.0,<7.0.0)
Requires-Dist: rasterio (>=1.3.10,<2.0.0)
Requires-Dist: shapely (>=2.0.4,<3.0.0)
Requires-Dist: torch (>=2.4.0,<3.0.0)
Requires-Dist: tqdm (>=4.66.4,<5.0.0)
Project-URL: Bug Tracker, https://github.com/Florian-Katerndahl/ForesTiler/issues
Project-URL: Repository, https://github.com/Florian-Katerndahl/ForesTiler
